<?xml version="1.0" encoding="UTF-8"?>
<!DOCTYPE mapper PUBLIC "-//mybatis.org//DTD Mapper 3.0//EN" "http://mybatis.org/dtd/mybatis-3-mapper.dtd">
<mapper namespace="com.github.security.dao.mapper.gen.SecResourcesMapper">
  <resultMap id="BaseResultMap" type="com.github.security.dao.entity.SecResources">
    <!--
      WARNING - @mbg.generated
      This element is automatically generated by MyBatis Generator, do not modify.
      This element was generated on Sun Dec 24 11:10:53 CST 2017.
    -->
    <id column="id" jdbcType="INTEGER" property="id" />
    <result column="ctime" jdbcType="TIMESTAMP" property="ctime" />
    <result column="mtime" jdbcType="TIMESTAMP" property="mtime" />
    <result column="version" jdbcType="INTEGER" property="version" />
    <result column="status" jdbcType="INTEGER" property="status" />
    <result column="mark" jdbcType="VARCHAR" property="mark" />
    <result column="name" jdbcType="VARCHAR" property="name" />
    <result column="operator" jdbcType="INTEGER" property="operator" />
    <result column="resource_key" jdbcType="VARCHAR" property="resourceKey" />
    <result column="type" jdbcType="SMALLINT" property="type" />
    <result column="uri" jdbcType="VARCHAR" property="uri" />
    <result column="parent_id" jdbcType="INTEGER" property="parentId" />
    <result column="level" jdbcType="VARCHAR" property="level" />
  </resultMap>
  <sql id="Example_Where_Clause">
    <!--
      WARNING - @mbg.generated
      This element is automatically generated by MyBatis Generator, do not modify.
      This element was generated on Sun Dec 24 11:10:53 CST 2017.
    -->
    <where>
      <foreach collection="oredCriteria" item="criteria" separator="or">
        <if test="criteria.valid">
          <trim prefix="(" prefixOverrides="and" suffix=")">
            <foreach collection="criteria.criteria" item="criterion">
              <choose>
                <when test="criterion.noValue">
                  and ${criterion.condition}
                </when>
                <when test="criterion.singleValue">
                  and ${criterion.condition} #{criterion.value}
                </when>
                <when test="criterion.betweenValue">
                  and ${criterion.condition} #{criterion.value} and #{criterion.secondValue}
                </when>
                <when test="criterion.listValue">
                  and ${criterion.condition}
                  <foreach close=")" collection="criterion.value" item="listItem" open="(" separator=",">
                    #{listItem}
                  </foreach>
                </when>
              </choose>
            </foreach>
          </trim>
        </if>
      </foreach>
    </where>
  </sql>
  <sql id="Update_By_Example_Where_Clause">
    <!--
      WARNING - @mbg.generated
      This element is automatically generated by MyBatis Generator, do not modify.
      This element was generated on Sun Dec 24 11:10:53 CST 2017.
    -->
    <where>
      <foreach collection="example.oredCriteria" item="criteria" separator="or">
        <if test="criteria.valid">
          <trim prefix="(" prefixOverrides="and" suffix=")">
            <foreach collection="criteria.criteria" item="criterion">
              <choose>
                <when test="criterion.noValue">
                  and ${criterion.condition}
                </when>
                <when test="criterion.singleValue">
                  and ${criterion.condition} #{criterion.value}
                </when>
                <when test="criterion.betweenValue">
                  and ${criterion.condition} #{criterion.value} and #{criterion.secondValue}
                </when>
                <when test="criterion.listValue">
                  and ${criterion.condition}
                  <foreach close=")" collection="criterion.value" item="listItem" open="(" separator=",">
                    #{listItem}
                  </foreach>
                </when>
              </choose>
            </foreach>
          </trim>
        </if>
      </foreach>
    </where>
  </sql>
  <sql id="Base_Column_List">
    <!--
      WARNING - @mbg.generated
      This element is automatically generated by MyBatis Generator, do not modify.
      This element was generated on Sun Dec 24 11:10:53 CST 2017.
    -->
    id, ctime, mtime, version, status, mark, name, operator, resource_key, type, uri, 
    parent_id, level
  </sql>
  <select id="selectByExample" parameterType="com.github.security.dao.entity.SecResourcesExample" resultMap="BaseResultMap">
    <!--
      WARNING - @mbg.generated
      This element is automatically generated by MyBatis Generator, do not modify.
      This element was generated on Sun Dec 24 11:10:53 CST 2017.
    -->
    select
    <if test="distinct">
      distinct
    </if>
    <include refid="Base_Column_List" />
    from sec_resources
    <if test="_parameter != null">
      <include refid="Example_Where_Clause" />
    </if>
    <if test="orderByClause != null">
      order by ${orderByClause}
    </if>
  </select>
  <select id="selectByPrimaryKey" parameterType="java.lang.Integer" resultMap="BaseResultMap">
    <!--
      WARNING - @mbg.generated
      This element is automatically generated by MyBatis Generator, do not modify.
      This element was generated on Sun Dec 24 11:10:53 CST 2017.
    -->
    select 
    <include refid="Base_Column_List" />
    from sec_resources
    where id = #{id,jdbcType=INTEGER}
  </select>
  <delete id="deleteByPrimaryKey" parameterType="java.lang.Integer">
    <!--
      WARNING - @mbg.generated
      This element is automatically generated by MyBatis Generator, do not modify.
      This element was generated on Sun Dec 24 11:10:53 CST 2017.
    -->
    delete from sec_resources
    where id = #{id,jdbcType=INTEGER}
  </delete>
  <delete id="deleteByExample" parameterType="com.github.security.dao.entity.SecResourcesExample">
    <!--
      WARNING - @mbg.generated
      This element is automatically generated by MyBatis Generator, do not modify.
      This element was generated on Sun Dec 24 11:10:53 CST 2017.
    -->
    delete from sec_resources
    <if test="_parameter != null">
      <include refid="Example_Where_Clause" />
    </if>
  </delete>
  <insert id="insert" parameterType="com.github.security.dao.entity.SecResources">
    <!--
      WARNING - @mbg.generated
      This element is automatically generated by MyBatis Generator, do not modify.
      This element was generated on Sun Dec 24 11:10:53 CST 2017.
    -->
    insert into sec_resources (id, ctime, mtime, 
      version, status, mark, 
      name, operator, resource_key, 
      type, uri, parent_id, 
      level)
    values (#{id,jdbcType=INTEGER}, #{ctime,jdbcType=TIMESTAMP}, #{mtime,jdbcType=TIMESTAMP}, 
      #{version,jdbcType=INTEGER}, #{status,jdbcType=INTEGER}, #{mark,jdbcType=VARCHAR}, 
      #{name,jdbcType=VARCHAR}, #{operator,jdbcType=INTEGER}, #{resourceKey,jdbcType=VARCHAR}, 
      #{type,jdbcType=SMALLINT}, #{uri,jdbcType=VARCHAR}, #{parentId,jdbcType=INTEGER}, 
      #{level,jdbcType=VARCHAR})
  </insert>
  <insert id="insertSelective" parameterType="com.github.security.dao.entity.SecResources">
    <!--
      WARNING - @mbg.generated
      This element is automatically generated by MyBatis Generator, do not modify.
      This element was generated on Sun Dec 24 11:10:53 CST 2017.
    -->
    insert into sec_resources
    <trim prefix="(" suffix=")" suffixOverrides=",">
      <if test="id != null">
        id,
      </if>
      <if test="ctime != null">
        ctime,
      </if>
      <if test="mtime != null">
        mtime,
      </if>
      <if test="version != null">
        version,
      </if>
      <if test="status != null">
        status,
      </if>
      <if test="mark != null">
        mark,
      </if>
      <if test="name != null">
        name,
      </if>
      <if test="operator != null">
        operator,
      </if>
      <if test="resourceKey != null">
        resource_key,
      </if>
      <if test="type != null">
        type,
      </if>
      <if test="uri != null">
        uri,
      </if>
      <if test="parentId != null">
        parent_id,
      </if>
      <if test="level != null">
        level,
      </if>
    </trim>
    <trim prefix="values (" suffix=")" suffixOverrides=",">
      <if test="id != null">
        #{id,jdbcType=INTEGER},
      </if>
      <if test="ctime != null">
        #{ctime,jdbcType=TIMESTAMP},
      </if>
      <if test="mtime != null">
        #{mtime,jdbcType=TIMESTAMP},
      </if>
      <if test="version != null">
        #{version,jdbcType=INTEGER},
      </if>
      <if test="status != null">
        #{status,jdbcType=INTEGER},
      </if>
      <if test="mark != null">
        #{mark,jdbcType=VARCHAR},
      </if>
      <if test="name != null">
        #{name,jdbcType=VARCHAR},
      </if>
      <if test="operator != null">
        #{operator,jdbcType=INTEGER},
      </if>
      <if test="resourceKey != null">
        #{resourceKey,jdbcType=VARCHAR},
      </if>
      <if test="type != null">
        #{type,jdbcType=SMALLINT},
      </if>
      <if test="uri != null">
        #{uri,jdbcType=VARCHAR},
      </if>
      <if test="parentId != null">
        #{parentId,jdbcType=INTEGER},
      </if>
      <if test="level != null">
        #{level,jdbcType=VARCHAR},
      </if>
    </trim>
  </insert>
  <select id="countByExample" parameterType="com.github.security.dao.entity.SecResourcesExample" resultType="java.lang.Long">
    <!--
      WARNING - @mbg.generated
      This element is automatically generated by MyBatis Generator, do not modify.
      This element was generated on Sun Dec 24 11:10:53 CST 2017.
    -->
    select count(*) from sec_resources
    <if test="_parameter != null">
      <include refid="Example_Where_Clause" />
    </if>
  </select>
  <update id="updateByExampleSelective" parameterType="map">
    <!--
      WARNING - @mbg.generated
      This element is automatically generated by MyBatis Generator, do not modify.
      This element was generated on Sun Dec 24 11:10:53 CST 2017.
    -->
    update sec_resources
    <set>
      <if test="record.id != null">
        id = #{record.id,jdbcType=INTEGER},
      </if>
      <if test="record.ctime != null">
        ctime = #{record.ctime,jdbcType=TIMESTAMP},
      </if>
      <if test="record.mtime != null">
        mtime = #{record.mtime,jdbcType=TIMESTAMP},
      </if>
      <if test="record.version != null">
        version = #{record.version,jdbcType=INTEGER},
      </if>
      <if test="record.status != null">
        status = #{record.status,jdbcType=INTEGER},
      </if>
      <if test="record.mark != null">
        mark = #{record.mark,jdbcType=VARCHAR},
      </if>
      <if test="record.name != null">
        name = #{record.name,jdbcType=VARCHAR},
      </if>
      <if test="record.operator != null">
        operator = #{record.operator,jdbcType=INTEGER},
      </if>
      <if test="record.resourceKey != null">
        resource_key = #{record.resourceKey,jdbcType=VARCHAR},
      </if>
      <if test="record.type != null">
        type = #{record.type,jdbcType=SMALLINT},
      </if>
      <if test="record.uri != null">
        uri = #{record.uri,jdbcType=VARCHAR},
      </if>
      <if test="record.parentId != null">
        parent_id = #{record.parentId,jdbcType=INTEGER},
      </if>
      <if test="record.level != null">
        level = #{record.level,jdbcType=VARCHAR},
      </if>
    </set>
    <if test="_parameter != null">
      <include refid="Update_By_Example_Where_Clause" />
    </if>
  </update>
  <update id="updateByExample" parameterType="map">
    <!--
      WARNING - @mbg.generated
      This element is automatically generated by MyBatis Generator, do not modify.
      This element was generated on Sun Dec 24 11:10:53 CST 2017.
    -->
    update sec_resources
    set id = #{record.id,jdbcType=INTEGER},
      ctime = #{record.ctime,jdbcType=TIMESTAMP},
      mtime = #{record.mtime,jdbcType=TIMESTAMP},
      version = #{record.version,jdbcType=INTEGER},
      status = #{record.status,jdbcType=INTEGER},
      mark = #{record.mark,jdbcType=VARCHAR},
      name = #{record.name,jdbcType=VARCHAR},
      operator = #{record.operator,jdbcType=INTEGER},
      resource_key = #{record.resourceKey,jdbcType=VARCHAR},
      type = #{record.type,jdbcType=SMALLINT},
      uri = #{record.uri,jdbcType=VARCHAR},
      parent_id = #{record.parentId,jdbcType=INTEGER},
      level = #{record.level,jdbcType=VARCHAR}
    <if test="_parameter != null">
      <include refid="Update_By_Example_Where_Clause" />
    </if>
  </update>
  <update id="updateByPrimaryKeySelective" parameterType="com.github.security.dao.entity.SecResources">
    <!--
      WARNING - @mbg.generated
      This element is automatically generated by MyBatis Generator, do not modify.
      This element was generated on Sun Dec 24 11:10:53 CST 2017.
    -->
    update sec_resources
    <set>
      <if test="ctime != null">
        ctime = #{ctime,jdbcType=TIMESTAMP},
      </if>
      <if test="mtime != null">
        mtime = #{mtime,jdbcType=TIMESTAMP},
      </if>
      <if test="version != null">
        version = #{version,jdbcType=INTEGER},
      </if>
      <if test="status != null">
        status = #{status,jdbcType=INTEGER},
      </if>
      <if test="mark != null">
        mark = #{mark,jdbcType=VARCHAR},
      </if>
      <if test="name != null">
        name = #{name,jdbcType=VARCHAR},
      </if>
      <if test="operator != null">
        operator = #{operator,jdbcType=INTEGER},
      </if>
      <if test="resourceKey != null">
        resource_key = #{resourceKey,jdbcType=VARCHAR},
      </if>
      <if test="type != null">
        type = #{type,jdbcType=SMALLINT},
      </if>
      <if test="uri != null">
        uri = #{uri,jdbcType=VARCHAR},
      </if>
      <if test="parentId != null">
        parent_id = #{parentId,jdbcType=INTEGER},
      </if>
      <if test="level != null">
        level = #{level,jdbcType=VARCHAR},
      </if>
    </set>
    where id = #{id,jdbcType=INTEGER}
  </update>
  <update id="updateByPrimaryKey" parameterType="com.github.security.dao.entity.SecResources">
    <!--
      WARNING - @mbg.generated
      This element is automatically generated by MyBatis Generator, do not modify.
      This element was generated on Sun Dec 24 11:10:53 CST 2017.
    -->
    update sec_resources
    set ctime = #{ctime,jdbcType=TIMESTAMP},
      mtime = #{mtime,jdbcType=TIMESTAMP},
      version = #{version,jdbcType=INTEGER},
      status = #{status,jdbcType=INTEGER},
      mark = #{mark,jdbcType=VARCHAR},
      name = #{name,jdbcType=VARCHAR},
      operator = #{operator,jdbcType=INTEGER},
      resource_key = #{resourceKey,jdbcType=VARCHAR},
      type = #{type,jdbcType=SMALLINT},
      uri = #{uri,jdbcType=VARCHAR},
      parent_id = #{parentId,jdbcType=INTEGER},
      level = #{level,jdbcType=VARCHAR}
    where id = #{id,jdbcType=INTEGER}
  </update>
  <insert id="insertList" parameterType="list">
    insert into sec_resources (id, ctime, mtime, version, status, mark, name, operator, resource_key, type, uri, parent_id, level) values 
    <foreach collection="list" index="index" item="item" separator=",">
      (#{item.id,jdbcType=INTEGER}, #{item.ctime,jdbcType=TIMESTAMP}, #{item.mtime,jdbcType=TIMESTAMP}, #{item.version,jdbcType=INTEGER}, #{item.status,jdbcType=INTEGER}, #{item.mark,jdbcType=VARCHAR}, #{item.name,jdbcType=VARCHAR}, #{item.operator,jdbcType=INTEGER}, #{item.resourceKey,jdbcType=VARCHAR}, #{item.type,jdbcType=SMALLINT}, #{item.uri,jdbcType=VARCHAR}, #{item.parentId,jdbcType=INTEGER}, #{item.level,jdbcType=VARCHAR})
    </foreach>
  </insert>
  <insert id="insertListSelective" parameterType="list">
    <foreach collection="list" index="index" item="item" separator=";">
      insert into sec_resources
      <trim prefix=" (" suffix=")" suffixOverrides=",">
        <if test="item.id != null">
          id,
        </if>
        <if test="item.ctime != null">
          ctime,
        </if>
        <if test="item.mtime != null">
          mtime,
        </if>
        <if test="item.version != null">
          version,
        </if>
        <if test="item.status != null">
          status,
        </if>
        <if test="item.mark != null">
          mark,
        </if>
        <if test="item.name != null">
          name,
        </if>
        <if test="item.operator != null">
          operator,
        </if>
        <if test="item.resourceKey != null">
          resource_key,
        </if>
        <if test="item.type != null">
          type,
        </if>
        <if test="item.uri != null">
          uri,
        </if>
        <if test="item.parentId != null">
          parent_id,
        </if>
        <if test="item.level != null">
          level,
        </if>
      </trim>
      <trim prefix="values (" suffix=")" suffixOverrides=",">
        <if test="item.id != null">
          #{item.id,jdbcType=INTEGER},
        </if>
        <if test="item.ctime != null">
          #{item.ctime,jdbcType=TIMESTAMP},
        </if>
        <if test="item.mtime != null">
          #{item.mtime,jdbcType=TIMESTAMP},
        </if>
        <if test="item.version != null">
          #{item.version,jdbcType=INTEGER},
        </if>
        <if test="item.status != null">
          #{item.status,jdbcType=INTEGER},
        </if>
        <if test="item.mark != null">
          #{item.mark,jdbcType=VARCHAR},
        </if>
        <if test="item.name != null">
          #{item.name,jdbcType=VARCHAR},
        </if>
        <if test="item.operator != null">
          #{item.operator,jdbcType=INTEGER},
        </if>
        <if test="item.resourceKey != null">
          #{item.resourceKey,jdbcType=VARCHAR},
        </if>
        <if test="item.type != null">
          #{item.type,jdbcType=SMALLINT},
        </if>
        <if test="item.uri != null">
          #{item.uri,jdbcType=VARCHAR},
        </if>
        <if test="item.parentId != null">
          #{item.parentId,jdbcType=INTEGER},
        </if>
        <if test="item.level != null">
          #{item.level,jdbcType=VARCHAR},
        </if>
      </trim>
    </foreach>
  </insert>
</mapper>